dukascript/__init__.py
dukascript/instruments.py
dukascript-0.0.8.dist-info/licenses/LICENSE
dukascript-0.0.8.dist-info/METADATA
dukascript-0.0.8.dist-info/WHEEL
dukascript-0.0.8.dist-info/top_level.txt
dukascript-0.0.8.dist-info/RECORD
