Metadata-Version: 2.4
Name: dukascript
Version: 0.0.8
Summary: Download tick data from Dukascopy Bank SA to local cache, and simulate time-ordered price streams
Author-email: Eghosa Osayande <osayandeeghosam@gmail.com>
License: MIT License
Project-URL: Homepage, https://github.com/Eghosa-Osayande/dukascript
Keywords: tick-data,forex-data,tick-api,ticks,dukascopy
Classifier: License :: OSI Approved :: MIT License
Classifier: Programming Language :: Python
Classifier: Programming Language :: Python :: 3
Requires-Python: >=3.10
License-File: LICENSE
Requires-Dist: pandas
Requires-Dist: requests
Provides-Extra: dev
Requires-Dist: build; extra == "dev"
Requires-Dist: twine; extra == "dev"
Dynamic: license-file
